flask_namespace/__init__.py
flask_namespace/exceptions.py
flask_namespace/helpers.py
flask_namespace/logger.py
flask_namespace/route.py
flask_namespace/signer.py
flask_namespace/socketio.py
flask_namespace-0.2.11.dist-info/LICENSE
flask_namespace-0.2.11.dist-info/METADATA
flask_namespace-0.2.11.dist-info/WHEEL
flask_namespace-0.2.11.dist-info/top_level.txt
flask_namespace-0.2.11.dist-info/RECORD
